PyPDFForm/__init__.py
PyPDFForm/adapter.py
PyPDFForm/ap.py
PyPDFForm/constants.py
PyPDFForm/coordinate.py
PyPDFForm/deprecation.py
PyPDFForm/filler.py
PyPDFForm/font.py
PyPDFForm/hooks.py
PyPDFForm/image.py
PyPDFForm/patterns.py
PyPDFForm/template.py
PyPDFForm/types.py
PyPDFForm/utils.py
PyPDFForm/watermark.py
PyPDFForm/wrapper.py
PyPDFForm/assets/__init__.py
PyPDFForm/assets/bedrock.py
PyPDFForm/assets/blank.py
PyPDFForm/middleware/__init__.py
PyPDFForm/middleware/base.py
PyPDFForm/middleware/checkbox.py
PyPDFForm/middleware/dropdown.py
PyPDFForm/middleware/image.py
PyPDFForm/middleware/radio.py
PyPDFForm/middleware/signature.py
PyPDFForm/middleware/text.py
PyPDFForm/raw/__init__.py
PyPDFForm/raw/image.py
PyPDFForm/raw/text.py
PyPDFForm/widgets/__init__.py
PyPDFForm/widgets/base.py
PyPDFForm/widgets/checkbox.py
PyPDFForm/widgets/dropdown.py
PyPDFForm/widgets/image.py
PyPDFForm/widgets/radio.py
PyPDFForm/widgets/signature.py
PyPDFForm/widgets/text.py
pypdfform-4.0.1.dist-info/licenses/LICENSE
pypdfform-4.0.1.dist-info/METADATA
pypdfform-4.0.1.dist-info/WHEEL
pypdfform-4.0.1.dist-info/top_level.txt
pypdfform-4.0.1.dist-info/RECORD
